fastdist/__init__.py
fastdist/fastdist.py
fastdist-1.1.6.dist-info/LICENSE
fastdist-1.1.6.dist-info/METADATA
fastdist-1.1.6.dist-info/WHEEL
fastdist-1.1.6.dist-info/top_level.txt
fastdist-1.1.6.dist-info/RECORD
