Metadata-Version: 2.1
Name: fastdist
Version: 1.1.6
Summary: Faster distance calculations in python using numba
Home-page: https://github.com/talboger/fastdist
Author: tal boger
Author-email: tboger10@gmail.com
Classifier: Programming Language :: Python :: 3
Classifier: License :: OSI Approved :: MIT License
Classifier: Operating System :: OS Independent
Requires-Python: >=3.6
License-File: LICENSE
